MANIFEST.in
README.md
setup.py
rdfframework/__init__.py
rdfframework/framework.py
rdfframework/loggingsetup.py
rdfframework.egg-info/PKG-INFO
rdfframework.egg-info/SOURCES.txt
rdfframework.egg-info/dependency_links.txt
rdfframework.egg-info/not-zip-safe
rdfframework.egg-info/requires.txt
rdfframework.egg-info/top_level.txt
rdfframework/configuration/__init__.py
rdfframework/configuration/rdfwconfig.py
rdfframework/connections/__init__.py
rdfframework/connections/blazegraph.py
rdfframework/connections/connmanager.py
rdfframework/connections/elasticconn.py
rdfframework/connections/fedoracommons.py
rdfframework/connections/rdflibconn.py
rdfframework/datamanager/__init__.py
rdfframework/datamanager/datamanager.py
rdfframework/datamanager/datastoremanager.py
rdfframework/datamanager/defmanager.py
rdfframework/datamanager/vocabularies/__init__.py
rdfframework/datamanager/vocabularies/adms.ttl
rdfframework/datamanager/vocabularies/bf.rdf
rdfframework/datamanager/vocabularies/bibliotek.ttl
rdfframework/datamanager/vocabularies/dc.ttl
rdfframework/datamanager/vocabularies/dcterm.ttl
rdfframework/datamanager/vocabularies/foaf.rdf
rdfframework/datamanager/vocabularies/owl.ttl
rdfframework/datamanager/vocabularies/rdf.ttl
rdfframework/datamanager/vocabularies/rdfs.ttl
rdfframework/datamanager/vocabularies/schema.nt
rdfframework/datamanager/vocabularies/skos.rdf
rdfframework/datamanager/vocabularies/vcard.ttl
rdfframework/datamanager/vocabularies/void.ttl
rdfframework/datamergers/__init__.py
rdfframework/datamergers/bftopic_merger.py
rdfframework/datasets/RemoteException.py
rdfframework/datasets/__init__.py
rdfframework/datasets/dataconverter.py
rdfframework/datasets/jsonquery.py
rdfframework/datasets/qryprocessors.py
rdfframework/datasets/rdfdatasets.py
rdfframework/datatypes/__init__.py
rdfframework/datatypes/datatypeerrors.py
rdfframework/datatypes/namespaces.py
rdfframework/datatypes/uriformatters.py
rdfframework/datatypes/xsdtypes.py
rdfframework/ingesters/__init__.py
rdfframework/ingesters/xmlingester.py
rdfframework/processors/__init__.py
rdfframework/processors/classprocessors.py
rdfframework/processors/propertyprocessors.py
rdfframework/rdfclass/__init__.py
