Metadata-Version: 1.1
Name: rdfframework
Version: 0.0.38
Summary: Application builder for KnowledgeLinks.io RDF applications.
Home-page: https://github.com/KnowledgeLinks/rdfframework/tree/development
Author: KnowledgeLinks,Jeremy Nelson,Mike Stabile
Author-email: knowledgelinks.io@gmail.com,jermnelson@gmail.com,mstabile75@gmail.com
License: UNKNOWN
Keywords: RDF linked data application builder
Platform: any
Classifier: Development Status :: 4 - Beta
Classifier: Environment :: Console
Classifier: Environment :: Web Environment
Classifier: Intended Audience :: Developers
Classifier: Operating System :: OS Independent
Classifier: Programming Language :: Python
Classifier: Programming Language :: Python :: 3.4
Classifier: Intended Audience :: Developers
Classifier: License :: OSI Approved :: GNU General Public License v3 (GPLv3)
Classifier: Topic :: Database
Classifier: Topic :: Text Processing :: General
Classifier: Topic :: Text Processing :: Indexing
Classifier: Topic :: Internet :: WWW/HTTP :: Dynamic Content
Classifier: Topic :: Internet :: WWW/HTTP :: WSGI :: Application
